[
  {
    "method": "亚参蒸鱼头",
    "price": 0,
    "available": true
  },
  {
    "method": "清蒸鱼头",
    "price": 0,
    "available": true
  },
  {
    "method": "潮州蒸鱼头",
    "price": 0,
    "available": true
  },
  {
    "method": "豆酱蒸鱼头",
    "price": 0,
    "available": true
  },
  {
    "method": "冬炎蒸鱼头",
    "price": 0,
    "available": true
  },
  {
    "method": "咖喱鱼头",
    "price": 0,
    "available": true
  },
  {
    "method": "沙煲红烧鱼头",
    "price": 0,
    "available": true
  },
  {
    "method": "红烧鱼头",
    "price": 0,
    "available": true
  },
  {
    "method": "豆酱鱼头",
    "price": 0,
    "available": true
  },
  {
    "method": "炒辣鱼头",
    "price": 0,
    "available": true
  }
]